{"textures":{"0":"modelengine:entity/camel"},"elements":[{"from":[6.7789154,-11.033573,4.5360622],"to":[9.778915,7.966427,8.036062],"faces":{"east":{"uv":[1.0,7.5,1.5,9.875],"tintindex":0,"rotation":0,"texture":"#0"},"south":{"uv":[2.0,8.75,2.375,11.125],"tintindex":0,"rotation":0,"texture":"#0"},"north":{"uv":[4.5,8.5,4.875,10.875],"tintindex":0,"rotation":0,"texture":"#0"},"west":{"uv":[1.5,7.5,2.0,9.875],"tintindex":0,"rotation":0,"texture":"#0"},"up":{"uv":[7.5,5.5,7.125,5.0],"tintindex":0,"rotation":0,"texture":"#0"},"down":{"uv":[7.875,5.0,7.5,5.5],"tintindex":0,"rotation":0,"texture":"#0"}}}]}